pyglass/__init__.py
pyglass/account/__init__.py
pyglass/account/account_types.py
pyglass/account/main.py
pyglass/block/__init__.py
pyglass/block/block_types.py
pyglass/block/main.py
pyglass/distribution/__init__.py
pyglass/distribution/distribution_types.py
pyglass/distribution/main.py
pyglass/exceptions.py
pyglass/known/__init__.py
pyglass/known/known_types.py
pyglass/known/main.py
pyglass/network/__init__.py
pyglass/network/main.py
pyglass/network/network_types.py
pyglass/representatives/__init__.py
pyglass/representatives/main.py
pyglass/representatives/representatives_types.py
pyglass_api-0.3.0.dist-info/LICENSE
pyglass_api-0.3.0.dist-info/METADATA
pyglass_api-0.3.0.dist-info/WHEEL
pyglass_api-0.3.0.dist-info/RECORD
